profiler_runit-0.1.4.dist-info/licenses/LICENSE
runit/__init__.py
runit/cli.py
runit/logging_config.py
runit/monitor.py
runit/plotting.py
runit/report.py
runit/utils.py
profiler_runit-0.1.4.dist-info/METADATA
profiler_runit-0.1.4.dist-info/WHEEL
profiler_runit-0.1.4.dist-info/entry_points.txt
profiler_runit-0.1.4.dist-info/top_level.txt
profiler_runit-0.1.4.dist-info/RECORD
