Metadata-Version: 2.4
Name: profiler-runit
Version: 0.1.4
Summary: Execute and profile cli commands
Author-email: NotesOfCliff <notesofcliff@gmail.com>
License-Expression: GPL-3.0-only
Requires-Python: >=3.9
License-File: LICENSE
Requires-Dist: psutil
Requires-Dist: plotext
Dynamic: license-file
